{
    "m_Version": 12,
    "DisplayName": "Seeds",
    "Icon": "Deliver",
    "Color": "FBFCFEFF",
    "IsExchange": 0,
    "InitStockPercent": 75.0,
    "Items": [
        {
            "ClassName": "pepperseedspack",
            "MaxPriceThreshold": 500,
            "MinPriceThreshold": 500,
            "SellPricePercent": 50,
            "MaxStockThreshold": 1,
            "MinStockThreshold": 1,
            "QuantityPercent": -1,
            "SpawnAttachments": [],
            "Variants": []
        },
        {
            "ClassName": "pumpkinseedspack",
            "MaxPriceThreshold": 550,
            "MinPriceThreshold": 550,
            "SellPricePercent": 50,
            "MaxStockThreshold": 1,
            "MinStockThreshold": 1,
            "QuantityPercent": -1,
            "SpawnAttachments": [],
            "Variants": []
        },
        {
            "ClassName": "tomatoseedspack",
            "MaxPriceThreshold": 500,
            "MinPriceThreshold": 500,
            "SellPricePercent": 50,
            "MaxStockThreshold": 1,
            "MinStockThreshold": 1,
            "QuantityPercent": -1,
            "SpawnAttachments": [],
            "Variants": []
        },
        {
            "ClassName": "zucchiniseedspack",
            "MaxPriceThreshold": 500,
            "MinPriceThreshold": 500,
            "SellPricePercent": 50,
            "MaxStockThreshold": 1,
            "MinStockThreshold": 1,
            "QuantityPercent": -1,
            "SpawnAttachments": [],
            "Variants": []
        },
        {
            "ClassName": "iM7s_SeedPack_BabyBatter",
            "MaxPriceThreshold": 100,
            "MinPriceThreshold": 100,
            "SellPricePercent": -1.0,
            "MaxStockThreshold": 100,
            "MinStockThreshold": 1,
            "QuantityPercent": -1,
            "SpawnAttachments": [],
            "Variants": []
        },
        {
            "ClassName": "iM7s_SeedPack_Barney",
            "MaxPriceThreshold": 100,
            "MinPriceThreshold": 100,
            "SellPricePercent": -1.0,
            "MaxStockThreshold": 100,
            "MinStockThreshold": 1,
            "QuantityPercent": -1,
            "SpawnAttachments": [],
            "Variants": []
        },
        {
            "ClassName": "iM7s_SeedPack_BlueCookies",
            "MaxPriceThreshold": 100,
            "MinPriceThreshold": 100,
            "SellPricePercent": -1.0,
            "MaxStockThreshold": 100,
            "MinStockThreshold": 1,
            "QuantityPercent": -1,
            "SpawnAttachments": [],
            "Variants": []
        },
        {
            "ClassName": "iM7s_SeedPack_Champagne",
            "MaxPriceThreshold": 100,
            "MinPriceThreshold": 100,
            "SellPricePercent": -1.0,
            "MaxStockThreshold": 100,
            "MinStockThreshold": 1,
            "QuantityPercent": -1,
            "SpawnAttachments": [],
            "Variants": []
        },
        {
            "ClassName": "iM7s_SeedPack_CheetahPiss",
            "MaxPriceThreshold": 100,
            "MinPriceThreshold": 100,
            "SellPricePercent": -1.0,
            "MaxStockThreshold": 100,
            "MinStockThreshold": 1,
            "QuantityPercent": -1,
            "SpawnAttachments": [],
            "Variants": []
        },
        {
            "ClassName": "iM7s_SeedPack_Gelato",
            "MaxPriceThreshold": 100,
            "MinPriceThreshold": 100,
            "SellPricePercent": -1.0,
            "MaxStockThreshold": 100,
            "MinStockThreshold": 1,
            "QuantityPercent": -1,
            "SpawnAttachments": [],
            "Variants": []
        },
        {
            "ClassName": "iM7s_SeedPack_Paragon",
            "MaxPriceThreshold": 100,
            "MinPriceThreshold": 100,
            "SellPricePercent": -1.0,
            "MaxStockThreshold": 100,
            "MinStockThreshold": 1,
            "QuantityPercent": -1,
            "SpawnAttachments": [],
            "Variants": []
        },
        {
            "ClassName": "iM7s_SeedPack_Coca",
            "MaxPriceThreshold": 100,
            "MinPriceThreshold": 100,
            "SellPricePercent": -1.0,
            "MaxStockThreshold": 100,
            "MinStockThreshold": 1,
            "QuantityPercent": -1,
            "SpawnAttachments": [],
            "Variants": []
        },
        {
            "ClassName": "iM7s_SeedPack_Poppy",
            "MaxPriceThreshold": 100,
            "MinPriceThreshold": 100,
            "SellPricePercent": -1.0,
            "MaxStockThreshold": 100,
            "MinStockThreshold": 1,
            "QuantityPercent": -1,
            "SpawnAttachments": [],
            "Variants": []
        },
        {
            "ClassName": "iM7s_SporeSyringe_BlueVeils",
            "MaxPriceThreshold": 10000,
            "MinPriceThreshold": 10000,
            "SellPricePercent": 50,
            "MaxStockThreshold": 100,
            "MinStockThreshold": 1,
            "QuantityPercent": -1,
            "SpawnAttachments": [],
            "Variants": []
        },
        {
            "ClassName": "iM7s_SporeSyringe_GhostCaps",
            "MaxPriceThreshold": 10000,
            "MinPriceThreshold": 10000,
            "SellPricePercent": 50,
            "MaxStockThreshold": 100,
            "MinStockThreshold": 1,
            "QuantityPercent": -1,
            "SpawnAttachments": [],
            "Variants": []
        },
        {
            "ClassName": "iM7s_SporeSyringe_GoldenTeacher",
            "MaxPriceThreshold": 10000,
            "MinPriceThreshold": 10000,
            "SellPricePercent": 50,
            "MaxStockThreshold": 100,
            "MinStockThreshold": 1,
            "QuantityPercent": -1,
            "SpawnAttachments": [],
            "Variants": []
        },
        {
            "ClassName": "iM7s_SporeSyringe_MysticVoid",
            "MaxPriceThreshold": 10000,
            "MinPriceThreshold": 10000,
            "SellPricePercent": 50,
            "MaxStockThreshold": 100,
            "MinStockThreshold": 1,
            "QuantityPercent": -1,
            "SpawnAttachments": [],
            "Variants": []
        },
        {
            "ClassName": "iM7s_SporeSyringe_Sunspores",
            "MaxPriceThreshold": 10000,
            "MinPriceThreshold": 10000,
            "SellPricePercent": 50,
            "MaxStockThreshold": 100,
            "MinStockThreshold": 1,
            "QuantityPercent": -1,
            "SpawnAttachments": [],
            "Variants": []
        }
    ]
}